README.rst
setup.cfg
setup.py
Aerate.egg-info/PKG-INFO
Aerate.egg-info/SOURCES.txt
Aerate.egg-info/dependency_links.txt
Aerate.egg-info/requires.txt
Aerate.egg-info/top_level.txt
aerate/__init__.py
aerate/auth.py
aerate/config.py
aerate/default_settings.py
aerate/errors.py
aerate/exception.py
aerate/falconapp.py
aerate/filter.py
aerate/middleware.py
aerate/resources.py
aerate/swagger.py
aerate/utils.py
aerate/validate.py
aerate/io/__init__.py
aerate/io/base.py
aerate/io/mongo/__init__.py
aerate/io/mongo/mongo.py
aerate/tests/__init__.py
aerate/tests/test_aerate.py
aerate/tests/test_client.py
aerate/tests/test_config.py
aerate/tests/test_datalayer.py
aerate/tests/test_fixtures.py
aerate/tests/test_middleware.py
aerate/tests/test_resources.py
aerate/tests/test_settings.py
aerate/tests/test_utils.py
aerate/tests/test_validation.py