Metadata-Version: 1.1
Name: Aerate
Version: 0.0.1.dev26
Summary: Aerate REST APIs: falcons with bravado and swagger.
Home-page: http://aerate.arable.com
Author: Kelly Caylor
Author-email: kelly@arable.com
License: BSD
Platform: any
Classifier: Development Status :: 4 - Beta
Classifier: Environment :: Web Environment
Classifier: Intended Audience :: Developers
Classifier: License :: OSI Approved :: BSD License
Classifier: Operating System :: OS Independent
Classifier: Programming Language :: Python
Classifier: Programming Language :: Python :: 2
Classifier: Programming Language :: Python :: 2.6
Classifier: Programming Language :: Python :: 2.7
Classifier: Programming Language :: Python :: 3
Classifier: Programming Language :: Python :: 3.3
Classifier: Programming Language :: Python :: 3.4
Classifier: Topic :: Internet :: WWW/HTTP :: Dynamic Content
